__init__.py
ez_setup.py
setup.py
svnpuppy.py
svnpuppy.egg-info/PKG-INFO
svnpuppy.egg-info/SOURCES.txt
svnpuppy.egg-info/dependency_links.txt
svnpuppy.egg-info/entry_points.txt
svnpuppy.egg-info/top_level.txt
svnpuppy.egg-info/zip-safe