Metadata-Version: 1.0
Name: svnpuppy
Version: 0.0.1
Summary: Subversion backup script
Home-page: http://chasingframes.co.cc
Author: Supreet Sethi
Author-email: supreet.sethi@gmail.com
License: GPL
Keywords: administration backup scm svn versioncontrol
Platform: UNKNOWN
Classifier: Development Status :: 4 - Beta
Classifier: Environment :: Console
Classifier: Intended Audience :: Developers
Classifier: Intended Audience :: System Administrators
Classifier: Natural Language :: English
Classifier: License :: OSI Approved :: GNU General Public License (GPL)
Classifier: Operating System :: OS Independent
Classifier: Programming Language :: Python
Classifier: Topic :: Software Development :: Version Control
Classifier: Topic :: System :: Archiving :: Backup
